<?xml version="1.0" encoding="utf-8" ?>
<hibernate-mapping xmlns="urn:nhibernate-mapping-2.2">
  <class name="com.Sconit.Entity.MasterData.CycleCountDetail, com.Sconit.Entity" table="CycleCountDet" lazy="false">
    <id name="Id" column="Id" type="Int32" unsaved-value="0" >
      <generator class="identity" />
    </id>
    <many-to-one name="CycleCount" column="OrderNo" class="com.Sconit.Entity.MasterData.CycleCount, com.Sconit.Entity" cascade="none" />
    <many-to-one name="Item" column="Item" class="com.Sconit.Entity.MasterData.Item, com.Sconit.Entity" cascade="none" />
    <property name="Qty" column="Qty" type="Decimal"  />
    <!--<many-to-one name="Hu" column="HuId" class="com.Sconit.Entity.MasterData.Hu, com.Sconit.Entity" cascade="none" />-->
    <property name="HuId" column="HuId" type="String" length="50" />
    <property name="LotNo" column="LotNo" type="String" length="50" />
    <!--<many-to-one name="StorageBin" column="Bin" class="com.Sconit.Entity.MasterData.StorageBin, com.Sconit.Entity" cascade="none" />-->
    <property name="StorageBin" column="Bin" type="String" length="50" />
    <property name="StartTime" column="StartTime" type="DateTime"/>
    <property name="EndTime" column="EndTime" type="DateTime"/>
    <property name="Memo" column="Memo" type="String" length="255" />
  </class>
</hibernate-mapping>
